{"dependencies":[{"name":"./redditapi","loc":{"line":1,"column":19}}],"generated":{"js":"'use strict';\n\nvar _redditapi = require('./redditapi');\n\nvar _redditapi2 = _interopRequireDefault(_redditapi);\n\nfunction _interopRequireDefault(obj) { return obj && obj.__esModule ? obj : { default: obj }; }\n\nconst searchForm = document.getElementById('search-form');\nconst searchInput = document.getElementById('search-input');\n\n//Form Event Listener\nsearchForm.addEventListener('submit', e => {\n    //Get Search Term\n    const searchTerm = searchInput.value;\n\n    //Get sort\n    const sortBy = document.querySelector('input[name=\"sortby\"]:checked').value;\n    //Get Limit\n    const searchLimit = document.getElementById('limit').value;\n\n    //Check input\n    if (searchTerm === '') {\n        //Show message\n        showMessage('Please add a search Term', 'alert-danger');\n    }\n\n    //Clear Input\n    searchInput.value = '';\n\n    //Search Reddit\n    _redditapi2.default.search(searchTerm, searchLimit, sortBy);\n\n    e.preventDefault();\n});\n\n//Show Message\nfunction showMessage(message, className) {\n    //Create div\n    const div = document.createElement('div');\n\n    //Add classes\n    div.className = `alert ${className}`;\n\n    //Add Text\n    div.appendChild(document.createTextNode(message));\n\n    //Get parent \n    const searchContainer = document.getElementById('search-container');\n\n    //Get Search\n    const search = document.getElementById('search');\n\n    //Insert the message\n    searchContainer.insertBefore(div, search);\n\n    //Timeout alert after 3 sec\n    setTimeout(function () {\n        document.querySelector('.alert').remove();\n    }, 3000);\n}","map":{"mappings":[{"generated":{"line":3,"column":0},"source":"index.js","original":{"line":1,"column":0}},{"generated":{"line":9,"column":0},"source":"index.js","original":{"line":3,"column":0}},{"name":"searchForm","generated":{"line":9,"column":6},"source":"index.js","original":{"line":3,"column":6}},{"name":"document","generated":{"line":9,"column":19},"source":"index.js","original":{"line":3,"column":19}},{"name":"getElementById","generated":{"line":9,"column":28},"source":"index.js","original":{"line":3,"column":28}},{"generated":{"line":9,"column":42},"source":"index.js","original":{"line":3,"column":19}},{"generated":{"line":9,"column":43},"source":"index.js","original":{"line":3,"column":43}},{"generated":{"line":9,"column":56},"source":"index.js","original":{"line":3,"column":19}},{"generated":{"line":9,"column":57},"source":"index.js","original":{"line":3,"column":0}},{"generated":{"line":10,"column":0},"source":"index.js","original":{"line":4,"column":0}},{"name":"searchInput","generated":{"line":10,"column":6},"source":"index.js","original":{"line":4,"column":6}},{"name":"document","generated":{"line":10,"column":20},"source":"index.js","original":{"line":4,"column":20}},{"name":"getElementById","generated":{"line":10,"column":29},"source":"index.js","original":{"line":4,"column":29}},{"generated":{"line":10,"column":43},"source":"index.js","original":{"line":4,"column":20}},{"generated":{"line":10,"column":44},"source":"index.js","original":{"line":4,"column":44}},{"generated":{"line":10,"column":58},"source":"index.js","original":{"line":4,"column":20}},{"generated":{"line":10,"column":59},"source":"index.js","original":{"line":4,"column":0}},{"generated":{"line":12,"column":0},"source":"index.js","original":{"line":6,"column":0}},{"name":"searchForm","generated":{"line":13,"column":0},"source":"index.js","original":{"line":7,"column":0}},{"name":"addEventListener","generated":{"line":13,"column":11},"source":"index.js","original":{"line":7,"column":11}},{"generated":{"line":13,"column":27},"source":"index.js","original":{"line":7,"column":0}},{"generated":{"line":13,"column":28},"source":"index.js","original":{"line":7,"column":28}},{"generated":{"line":13,"column":36},"source":"index.js","original":{"line":7,"column":0}},{"name":"e","generated":{"line":13,"column":38},"source":"index.js","original":{"line":7,"column":38}},{"generated":{"line":13,"column":43},"source":"index.js","original":{"line":7,"column":43}},{"generated":{"line":14,"column":0},"source":"index.js","original":{"line":8,"column":4}},{"generated":{"line":15,"column":0},"source":"index.js","original":{"line":9,"column":4}},{"name":"searchTerm","generated":{"line":15,"column":10},"source":"index.js","original":{"line":9,"column":10}},{"name":"searchInput","generated":{"line":15,"column":23},"source":"index.js","original":{"line":9,"column":23}},{"name":"value","generated":{"line":15,"column":35},"source":"index.js","original":{"line":9,"column":35}},{"generated":{"line":15,"column":40},"source":"index.js","original":{"line":9,"column":4}},{"generated":{"line":17,"column":0},"source":"index.js","original":{"line":11,"column":4}},{"generated":{"line":18,"column":0},"source":"index.js","original":{"line":12,"column":4}},{"name":"sortBy","generated":{"line":18,"column":10},"source":"index.js","original":{"line":12,"column":10}},{"name":"document","generated":{"line":18,"column":19},"source":"index.js","original":{"line":12,"column":19}},{"name":"querySelector","generated":{"line":18,"column":28},"source":"index.js","original":{"line":12,"column":28}},{"generated":{"line":18,"column":41},"source":"index.js","original":{"line":12,"column":19}},{"generated":{"line":18,"column":42},"source":"index.js","original":{"line":12,"column":42}},{"generated":{"line":18,"column":72},"source":"index.js","original":{"line":12,"column":19}},{"name":"value","generated":{"line":18,"column":74},"source":"index.js","original":{"line":12,"column":74}},{"generated":{"line":18,"column":79},"source":"index.js","original":{"line":12,"column":4}},{"generated":{"line":19,"column":0},"source":"index.js","original":{"line":13,"column":4}},{"generated":{"line":20,"column":0},"source":"index.js","original":{"line":14,"column":4}},{"name":"searchLimit","generated":{"line":20,"column":10},"source":"index.js","original":{"line":14,"column":10}},{"name":"document","generated":{"line":20,"column":24},"source":"index.js","original":{"line":14,"column":24}},{"name":"getElementById","generated":{"line":20,"column":33},"source":"index.js","original":{"line":14,"column":33}},{"generated":{"line":20,"column":47},"source":"index.js","original":{"line":14,"column":24}},{"generated":{"line":20,"column":48},"source":"index.js","original":{"line":14,"column":48}},{"generated":{"line":20,"column":55},"source":"index.js","original":{"line":14,"column":24}},{"name":"value","generated":{"line":20,"column":57},"source":"index.js","original":{"line":14,"column":57}},{"generated":{"line":20,"column":62},"source":"index.js","original":{"line":14,"column":4}},{"generated":{"line":22,"column":0},"source":"index.js","original":{"line":16,"column":4}},{"generated":{"line":23,"column":0},"source":"index.js","original":{"line":17,"column":4}},{"name":"searchTerm","generated":{"line":23,"column":8},"source":"index.js","original":{"line":17,"column":7}},{"generated":{"line":23,"column":23},"source":"index.js","original":{"line":17,"column":22}},{"generated":{"line":23,"column":25},"source":"index.js","original":{"line":17,"column":4}},{"generated":{"line":23,"column":27},"source":"index.js","original":{"line":17,"column":25}},{"generated":{"line":24,"column":0},"source":"index.js","original":{"line":18,"column":8}},{"name":"showMessage","generated":{"line":25,"column":0},"source":"index.js","original":{"line":19,"column":8}},{"generated":{"line":25,"column":20},"source":"index.js","original":{"line":19,"column":20}},{"generated":{"line":25,"column":46},"source":"index.js","original":{"line":19,"column":8}},{"generated":{"line":25,"column":48},"source":"index.js","original":{"line":19,"column":48}},{"generated":{"line":25,"column":62},"source":"index.js","original":{"line":19,"column":8}},{"generated":{"line":26,"column":0},"source":"index.js","original":{"line":20,"column":5}},{"generated":{"line":28,"column":0},"source":"index.js","original":{"line":22,"column":4}},{"name":"searchInput","generated":{"line":29,"column":0},"source":"index.js","original":{"line":23,"column":4}},{"name":"value","generated":{"line":29,"column":16},"source":"index.js","original":{"line":23,"column":16}},{"generated":{"line":29,"column":21},"source":"index.js","original":{"line":23,"column":4}},{"generated":{"line":29,"column":24},"source":"index.js","original":{"line":23,"column":24}},{"generated":{"line":29,"column":26},"source":"index.js","original":{"line":23,"column":4}},{"generated":{"line":31,"column":0},"source":"index.js","original":{"line":25,"column":4}},{"generated":{"line":32,"column":0},"source":"index.js","original":{"line":26,"column":4}},{"name":"search","generated":{"line":32,"column":24},"source":"index.js","original":{"line":26,"column":11}},{"generated":{"line":32,"column":30},"source":"index.js","original":{"line":26,"column":4}},{"name":"searchTerm","generated":{"line":32,"column":31},"source":"index.js","original":{"line":26,"column":18}},{"generated":{"line":32,"column":41},"source":"index.js","original":{"line":26,"column":4}},{"name":"searchLimit","generated":{"line":32,"column":43},"source":"index.js","original":{"line":26,"column":30}},{"generated":{"line":32,"column":54},"source":"index.js","original":{"line":26,"column":4}},{"name":"sortBy","generated":{"line":32,"column":56},"source":"index.js","original":{"line":26,"column":43}},{"generated":{"line":32,"column":62},"source":"index.js","original":{"line":26,"column":4}},{"name":"e","generated":{"line":34,"column":0},"source":"index.js","original":{"line":28,"column":4}},{"name":"preventDefault","generated":{"line":34,"column":6},"source":"index.js","original":{"line":28,"column":6}},{"generated":{"line":34,"column":20},"source":"index.js","original":{"line":28,"column":4}},{"generated":{"line":35,"column":0},"source":"index.js","original":{"line":30,"column":1}},{"generated":{"line":35,"column":1},"source":"index.js","original":{"line":7,"column":0}},{"generated":{"line":37,"column":0},"source":"index.js","original":{"line":32,"column":4}},{"generated":{"line":38,"column":0},"source":"index.js","original":{"line":33,"column":4}},{"name":"showMessage","generated":{"line":38,"column":9},"source":"index.js","original":{"line":33,"column":13}},{"generated":{"line":38,"column":20},"source":"index.js","original":{"line":33,"column":4}},{"name":"message","generated":{"line":38,"column":21},"source":"index.js","original":{"line":33,"column":25}},{"generated":{"line":38,"column":28},"source":"index.js","original":{"line":33,"column":4}},{"name":"className","generated":{"line":38,"column":30},"source":"index.js","original":{"line":33,"column":34}},{"generated":{"line":38,"column":39},"source":"index.js","original":{"line":33,"column":4}},{"generated":{"line":38,"column":41},"source":"index.js","original":{"line":33,"column":44}},{"generated":{"line":39,"column":0},"source":"index.js","original":{"line":34,"column":8}},{"generated":{"line":40,"column":0},"source":"index.js","original":{"line":35,"column":8}},{"name":"div","generated":{"line":40,"column":10},"source":"index.js","original":{"line":35,"column":14}},{"name":"document","generated":{"line":40,"column":16},"source":"index.js","original":{"line":35,"column":20}},{"name":"createElement","generated":{"line":40,"column":25},"source":"index.js","original":{"line":35,"column":29}},{"generated":{"line":40,"column":38},"source":"index.js","original":{"line":35,"column":20}},{"generated":{"line":40,"column":39},"source":"index.js","original":{"line":35,"column":43}},{"generated":{"line":40,"column":44},"source":"index.js","original":{"line":35,"column":20}},{"generated":{"line":40,"column":45},"source":"index.js","original":{"line":35,"column":8}},{"generated":{"line":42,"column":0},"source":"index.js","original":{"line":37,"column":8}},{"name":"div","generated":{"line":43,"column":0},"source":"index.js","original":{"line":38,"column":8}},{"name":"className","generated":{"line":43,"column":8},"source":"index.js","original":{"line":38,"column":12}},{"generated":{"line":43,"column":17},"source":"index.js","original":{"line":38,"column":8}},{"generated":{"line":43,"column":20},"source":"index.js","original":{"line":38,"column":25}},{"name":"className","generated":{"line":43,"column":29},"source":"index.js","original":{"line":38,"column":33}},{"generated":{"line":43,"column":38},"source":"index.js","original":{"line":38,"column":43}},{"generated":{"line":43,"column":40},"source":"index.js","original":{"line":38,"column":8}},{"generated":{"line":45,"column":0},"source":"index.js","original":{"line":40,"column":8}},{"name":"div","generated":{"line":46,"column":0},"source":"index.js","original":{"line":41,"column":8}},{"name":"appendChild","generated":{"line":46,"column":8},"source":"index.js","original":{"line":41,"column":12}},{"generated":{"line":46,"column":19},"source":"index.js","original":{"line":41,"column":8}},{"name":"document","generated":{"line":46,"column":20},"source":"index.js","original":{"line":41,"column":24}},{"name":"createTextNode","generated":{"line":46,"column":29},"source":"index.js","original":{"line":41,"column":33}},{"generated":{"line":46,"column":43},"source":"index.js","original":{"line":41,"column":24}},{"name":"message","generated":{"line":46,"column":44},"source":"index.js","original":{"line":41,"column":48}},{"generated":{"line":46,"column":51},"source":"index.js","original":{"line":41,"column":24}},{"generated":{"line":46,"column":52},"source":"index.js","original":{"line":41,"column":8}},{"generated":{"line":48,"column":0},"source":"index.js","original":{"line":43,"column":8}},{"generated":{"line":49,"column":0},"source":"index.js","original":{"line":44,"column":8}},{"name":"searchContainer","generated":{"line":49,"column":10},"source":"index.js","original":{"line":44,"column":14}},{"name":"document","generated":{"line":49,"column":28},"source":"index.js","original":{"line":44,"column":32}},{"name":"getElementById","generated":{"line":49,"column":37},"source":"index.js","original":{"line":44,"column":41}},{"generated":{"line":49,"column":51},"source":"index.js","original":{"line":44,"column":32}},{"generated":{"line":49,"column":52},"source":"index.js","original":{"line":44,"column":56}},{"generated":{"line":49,"column":70},"source":"index.js","original":{"line":44,"column":32}},{"generated":{"line":49,"column":71},"source":"index.js","original":{"line":44,"column":8}},{"generated":{"line":51,"column":0},"source":"index.js","original":{"line":46,"column":8}},{"generated":{"line":52,"column":0},"source":"index.js","original":{"line":47,"column":8}},{"name":"search","generated":{"line":52,"column":10},"source":"index.js","original":{"line":47,"column":14}},{"name":"document","generated":{"line":52,"column":19},"source":"index.js","original":{"line":47,"column":23}},{"name":"getElementById","generated":{"line":52,"column":28},"source":"index.js","original":{"line":47,"column":32}},{"generated":{"line":52,"column":42},"source":"index.js","original":{"line":47,"column":23}},{"generated":{"line":52,"column":43},"source":"index.js","original":{"line":47,"column":47}},{"generated":{"line":52,"column":51},"source":"index.js","original":{"line":47,"column":23}},{"generated":{"line":52,"column":52},"source":"index.js","original":{"line":47,"column":8}},{"generated":{"line":54,"column":0},"source":"index.js","original":{"line":49,"column":8}},{"name":"searchContainer","generated":{"line":55,"column":0},"source":"index.js","original":{"line":50,"column":8}},{"name":"insertBefore","generated":{"line":55,"column":20},"source":"index.js","original":{"line":50,"column":24}},{"generated":{"line":55,"column":32},"source":"index.js","original":{"line":50,"column":8}},{"name":"div","generated":{"line":55,"column":33},"source":"index.js","original":{"line":50,"column":37}},{"generated":{"line":55,"column":36},"source":"index.js","original":{"line":50,"column":8}},{"name":"search","generated":{"line":55,"column":38},"source":"index.js","original":{"line":50,"column":42}},{"generated":{"line":55,"column":44},"source":"index.js","original":{"line":50,"column":8}},{"generated":{"line":57,"column":0},"source":"index.js","original":{"line":52,"column":8}},{"name":"setTimeout","generated":{"line":58,"column":0},"source":"index.js","original":{"line":53,"column":8}},{"generated":{"line":58,"column":15},"source":"index.js","original":{"line":53,"column":19}},{"generated":{"line":58,"column":27},"source":"index.js","original":{"line":53,"column":30}},{"name":"document","generated":{"line":59,"column":0},"source":"index.js","original":{"line":54,"column":12}},{"name":"querySelector","generated":{"line":59,"column":17},"source":"index.js","original":{"line":54,"column":21}},{"generated":{"line":59,"column":30},"source":"index.js","original":{"line":54,"column":12}},{"generated":{"line":59,"column":31},"source":"index.js","original":{"line":54,"column":35}},{"generated":{"line":59,"column":39},"source":"index.js","original":{"line":54,"column":12}},{"name":"remove","generated":{"line":59,"column":41},"source":"index.js","original":{"line":54,"column":45}},{"generated":{"line":59,"column":47},"source":"index.js","original":{"line":54,"column":12}},{"generated":{"line":60,"column":0},"source":"index.js","original":{"line":55,"column":9}},{"generated":{"line":60,"column":5},"source":"index.js","original":{"line":53,"column":8}},{"generated":{"line":60,"column":7},"source":"index.js","original":{"line":55,"column":11}},{"generated":{"line":60,"column":11},"source":"index.js","original":{"line":53,"column":8}},{"generated":{"line":61,"column":0},"source":"index.js","original":{"line":56,"column":5}}],"sources":{"index.js":"import reddit from './redditapi';\r\n\r\nconst searchForm = document.getElementById('search-form');\r\nconst searchInput = document.getElementById('search-input');\r\n\r\n//Form Event Listener\r\nsearchForm.addEventListener('submit', e => {\r\n    //Get Search Term\r\n    const searchTerm = searchInput.value;\r\n\r\n    //Get sort\r\n    const sortBy = document.querySelector('input[name=\"sortby\"]:checked').value;\r\n    //Get Limit\r\n    const searchLimit = document.getElementById('limit').value;\r\n\r\n    //Check input\r\n    if(searchTerm === ''){\r\n        //Show message\r\n        showMessage('Please add a search Term', 'alert-danger');\r\n    }\r\n\r\n    //Clear Input\r\n    searchInput.value = '';\r\n\r\n    //Search Reddit\r\n    reddit.search(searchTerm, searchLimit, sortBy);\r\n\r\n    e.preventDefault();\r\n\r\n});\r\n\r\n    //Show Message\r\n    function showMessage(message, className){\r\n        //Create div\r\n        const div = document.createElement('div');\r\n\r\n        //Add classes\r\n        div.className = `alert ${className}`;\r\n\r\n        //Add Text\r\n        div.appendChild(document.createTextNode(message));\r\n\r\n        //Get parent \r\n        const searchContainer = document.getElementById('search-container');\r\n\r\n        //Get Search\r\n        const search = document.getElementById('search');\r\n\r\n        //Insert the message\r\n        searchContainer.insertBefore(div, search);\r\n\r\n        //Timeout alert after 3 sec\r\n        setTimeout(function() {\r\n            document.querySelector('.alert').remove();\r\n        }, 3000);\r\n    }"},"lineCount":null}},"hash":"b885084b8806a239a66ef569d4d3e168","cacheData":{"env":{}}}